setup.py
sqlite2json/__init__.py
sqlite2json.egg-info/PKG-INFO
sqlite2json.egg-info/SOURCES.txt
sqlite2json.egg-info/dependency_links.txt
sqlite2json.egg-info/entry_points.txt
sqlite2json.egg-info/top_level.txt