Metadata-Version: 1.0
Name: sqlite2json
Version: 1.0.1
Summary: SQLite to JSON converter
Home-page: https://github.com/john-g-g/sqlite2json
Author: John Gerlock
Author-email: john@pikkey.com
License: GNU GENERAL PUBLIC LICENSE
